src/__init__.py
src/traindex_cli.py
traindexcli-0.1.5.dist-info/LICENSE.txt
traindexcli-0.1.5.dist-info/METADATA
traindexcli-0.1.5.dist-info/WHEEL
traindexcli-0.1.5.dist-info/entry_points.txt
traindexcli-0.1.5.dist-info/top_level.txt
traindexcli-0.1.5.dist-info/RECORD
