Metadata-Version: 2.1
Name: traindexcli
Version: 0.1.5
Summary: Demo Package for traindex-cli.
Home-page: https://www.traindex.io/
Author: Eshban Suleman
Author-email: eshban@foretheta.com
License: MIT
Download-URL: https://github.com/traindex/traindex-cli/archive/v0.1.5.tar.gz
Keywords: traindex-cli,traindex_cli,traindexcli,traindex
Platform: UNKNOWN
Classifier: Development Status :: 3 - Alpha
Classifier: Environment :: Console
Classifier: Intended Audience :: Developers
Classifier: License :: OSI Approved :: BSD License
Classifier: Operating System :: POSIX
Classifier: Operating System :: MacOS
Classifier: Operating System :: Unix
Classifier: Operating System :: Microsoft :: Windows
Classifier: Programming Language :: Python
Classifier: Programming Language :: Python :: 2
Classifier: Programming Language :: Python :: 3
Classifier: Topic :: Software Development :: Libraries :: Python Modules
Requires-Dist: progressbar (==2.5)
